project/__init__.py
project/rds_uploader/__init__.py
project/rds_uploader/rds_module.py
project/scraper/__init__.py
project/scraper/__main__.py
project/scraper/scraper.py
cyberattacksscraper-0.0.1.dist-info/LICENSE
cyberattacksscraper-0.0.1.dist-info/METADATA
cyberattacksscraper-0.0.1.dist-info/WHEEL
cyberattacksscraper-0.0.1.dist-info/top_level.txt
cyberattacksscraper-0.0.1.dist-info/RECORD
