Metadata-Version: 2.1
Name: cyberattacksscraper
Version: 0.0.1
Summary: Web scraper that scrapes cyber attacks data from the Council on Foreign Relations Cyber Operations Tracker,  .
Home-page: https://github.com/anademarr/Software-Engineering-project
Author: Ana-Maria Dicu
License: MIT
Platform: UNKNOWN
License-File: LICENSE
Requires-Dist: selenium
Requires-Dist: pandas
Requires-Dist: sqlalchemy
